CHANGELOG.rst
LICENSE.txt
MANIFEST.in
NOTES.txt
README.rst
TODO.txt
VERSION.txt
setup.cfg
setup.py
test-requirements.txt
dnssync/__init__.py
dnssync.egg-info/PKG-INFO
dnssync.egg-info/SOURCES.txt
dnssync.egg-info/dependency_links.txt
dnssync.egg-info/entry_points.txt
dnssync.egg-info/requires.txt
dnssync.egg-info/top_level.txt
dnssync.egg-info/zip-safe
dnssync/api/__init__.py
dnssync/api/cli.py
dnssync/api/driver.py
dnssync/api/duration.py
dnssync/api/engine.py
dnssync/api/error.py
dnssync/api/i18n.py
dnssync/api/record.py
dnssync/api/util.py
dnssync/services/__init__.py
dnssync/services/domainmonster/__init__.py
dnssync/services/domainmonster/driver.py
dnssync/services/domainmonster/parser.py
dnssync/services/domainmonster/test.py
dnssync/services/powerdns/__init__.py
dnssync/services/powerdns/driver.py
dnssync/services/powerdns/protocol.py
dnssync/services/registerly/__init__.py
dnssync/services/registerly/driver.py
dnssync/services/registerly/parser.py
dnssync/services/registerly/test_parser.py
dnssync/services/zoneedit/__init__.py
dnssync/services/zoneedit/driver.py
dnssync/services/zoneedit/parser.py
dnssync/services/zoneedit/test_parser.py