Metadata-Version: 1.1
Name: dnssync
Version: 0.2.7
Summary: Command line client to synchronize DNS hosted zones with local zone files
Home-page: http://github.com/metagriffin/dnssync
Author: metagriffin
Author-email: mg.pypi@metagriffin.net
License: GPLv3+
Keywords: dns zone synchronize download upload diff client command line cli powerdns
Platform: any
Classifier: Development Status :: 4 - Beta
Classifier: Environment :: Console
Classifier: Intended Audience :: System Administrators
Classifier: Programming Language :: Python
Classifier: Operating System :: OS Independent
Classifier: Natural Language :: English
Classifier: License :: OSI Approved :: GNU General Public License v3 or later (GPLv3+)
